unifiedcatalogpy/__init__.py
unifiedcatalogpy/api_client.py
unifiedcatalogpy/client.py
unifiedcatalogpy/models.py
unifiedcatalogpy/utils.py
unifiedcatalogpy-0.0.5.dist-info/LICENSE
unifiedcatalogpy-0.0.5.dist-info/METADATA
unifiedcatalogpy-0.0.5.dist-info/WHEEL
unifiedcatalogpy-0.0.5.dist-info/top_level.txt
unifiedcatalogpy-0.0.5.dist-info/RECORD
