Metadata-Version: 2.2
Name: unifiedcatalogpy
Version: 0.0.5
Summary: A Python client for interacting with the Microsoft Purview Unified Catalog API.
Author: Olaf Wrieden
License: MIT License
Project-URL: Homepage, https://github.com/olafwrieden/unifiedcatalogpy
Project-URL: Documentation, https://github.com/olafwrieden/unifiedcatalogpy
Project-URL: Repository, https://github.com/olafwrieden/unifiedcatalogpy.git
Project-URL: Bug Tracker, https://github.com/olafwrieden/unifiedcatalogpy/issues
Project-URL: Changelog, https://github.com/olafwrieden/unifiedcatalogpy/commits/main/
Keywords: Microsoft Purview,Unified Catalog,Purview,Data Governance,Data Catalog
Classifier: Programming Language :: Python :: 3.9
Classifier: Intended Audience :: Developers
Classifier: License :: OSI Approved :: MIT License
Classifier: Operating System :: OS Independent
Requires-Python: >=3.9
License-File: LICENSE
Requires-Dist: requests
